function_sampler/sampler.py
function_sampler/regex_constants.py
function_sampler/logger.py
function_sampler/__init__.py
function_sampler/utils.py
function_sampler/cache.py
function_sampler/json.py
function_sampler/config/__init__.py
function_sampler/config/token_mapper.py
function_sampler/config/utils.py
function_sampler/config/config.py
function_sampler/fsm/__init__.py
function_sampler/fsm/regex.py
function_sampler/fsm/utils.py
function_sampler/fsm/tokenizer_fsm_patch.py
function_sampler/fsm/fsm_utils.cpython-39-aarch64-linux-gnu.so
function_sampler-0.2.1.dist-info/METADATA
function_sampler-0.2.1.dist-info/top_level.txt
function_sampler-0.2.1.dist-info/WHEEL
function_sampler-0.2.1.dist-info/RECORD
function_sampler-0.2.1.dist-info/LICENSE
