Metadata-Version: 2.1
Name: function-sampler
Version: 0.2.1
Summary: Function calling Logit Sampler
Home-page: https://github.com/unaidedelf8777/function-sampler/
Author: unaidedelf8777
Author-email: thwackyy.y@gmail.com
License: Apache 2.0
Classifier: Programming Language :: Rust
Classifier: Programming Language :: Python :: Implementation :: CPython
Classifier: Programming Language :: Python :: Implementation :: PyPy
Requires-Python: >=3.9
License-File: LICENSE
